fkv/__init__.py
fkv/main.py
fkv/parser.py
fkv/parsers/key.py
fkv/parsers/primatives.py
fkv/test/test_key.py
fkv/test/test_main.py
fkv/test/test_primitives.py
fkv-0.1.3.dist-info/METADATA
fkv-0.1.3.dist-info/WHEEL
fkv-0.1.3.dist-info/entry_points.txt
fkv-0.1.3.dist-info/RECORD
