Metadata-Version: 2.1
Name: fkv
Version: 0.1.3
Summary: 
Author: Blake Smith
Author-email: blake.woodsmith@gmail.com
Requires-Python: >=3.12,<4.0
Classifier: Programming Language :: Python :: 3
Classifier: Programming Language :: Python :: 3.12
Requires-Dist: parsy (>=2.1,<3.0)
